kubetop/__init__.py
kubetop/_metadata.py
kubetop/_runmany.py
kubetop/_runonce.py
kubetop/_script.py
kubetop/_textrenderer.py
kubetop/_topdata.py
kubetop/_twistmain.py
kubetop/test/__init__.py
kubetop/test/test_script.py
kubetop/test/test_textrenderer.py
kubetop/test/test_topdata.py
kubetop-17.4.17.1.dist-info/DESCRIPTION.rst
kubetop-17.4.17.1.dist-info/METADATA
kubetop-17.4.17.1.dist-info/RECORD
kubetop-17.4.17.1.dist-info/WHEEL
kubetop-17.4.17.1.dist-info/entry_points.txt
kubetop-17.4.17.1.dist-info/metadata.json
kubetop-17.4.17.1.dist-info/top_level.txt
