Metadata-Version: 2.0
Name: kubetop
Version: 17.4.17.1
Summary: A top(1)-like tool for Kubernetes.
Home-page: https://github.com/leastauthority.com/kubetop
Author: kubetop Developers
Author-email: UNKNOWN
License: MIT
Platform: UNKNOWN
Requires-Dist: bitmath
Requires-Dist: attr
Requires-Dist: pyyaml
Requires-Dist: twisted[tls]
Requires-Dist: treq
Requires-Dist: txkube
Provides-Extra: dev
Requires-Dist: hypothesis; extra == 'dev'
